PyCESim/PyCESim.py
PyCESim/__init__.py
PyCESim-0.0.1.dist-info/LICENSE
PyCESim-0.0.1.dist-info/METADATA
PyCESim-0.0.1.dist-info/WHEEL
PyCESim-0.0.1.dist-info/top_level.txt
PyCESim-0.0.1.dist-info/RECORD
