Metadata-Version: 2.1
Name: PyCESim
Version: 0.0.1
Summary: PyCESim - classical simulation of Coulomb explosion
Home-page: UNKNOWN
Author: Felix Allum
Author-email: <fallum@stanford.edu
License: UNKNOWN
Keywords: Coulomb explosion
Platform: UNKNOWN
License-File: LICENSE
Requires-Dist: cclib
